{"coord":{"lon":20.46,"lat":44.81},"weather":[{"id":804,"main":"Clouds","description":"overcast clouds","icon":"04n"}],"base":"stations","main":{"temp":7.49,"feels_like":6.21,"temp_min":5.92,"temp_max":7.64,"pressure":1022,"humidity":87,"sea_level":1022,"grnd_level":1006},"visibility":8000,"wind":{"speed":2.06,"deg":190},"clouds":{"all":89},"dt":1738274179,"sys":{"type":2,"id":2037836,"country":"RS","sunrise":1738216788,"sunset":1738251777},"timezone":3600,"id":792680,"name":"Belgrade","cod":200}