{"coord":{"lon":20.4582,"lat":44.8093},"weather":[{"id":741,"main":"Fog","description":"fog","icon":"50n"},{"id":701,"main":"Mist","description":"mist","icon":"50n"}],"base":"stations","main":{"temp":3.42,"feels_like":3.42,"temp_min":0.92,"temp_max":4.35,"pressure":1019,"humidity":100},"visibility":5000,"wind":{"speed":0,"deg":0},"clouds":{"all":53},"dt":1697604396,"sys":{"type":1,"id":7028,"country":"RS","sunrise":1697604998,"sunset":1697644191},"timezone":7200,"id":865971,"name":"Stari Grad","cod":200}