{"coord":{"lon":20.46,"lat":44.81},"weather":[{"id":520,"main":"Rain","description":"light intensity shower rain","icon":"09d"}],"base":"stations","main":{"temp":21.62,"feels_like":22.14,"temp_min":20.97,"temp_max":24.92,"pressure":1007,"humidity":88},"visibility":10000,"wind":{"speed":6.69,"deg":110},"rain":{"1h":0.25},"clouds":{"all":40},"dt":1695311782,"sys":{"type":2,"id":2037836,"country":"RS","sunrise":1695270204,"sunset":1695314371},"timezone":7200,"id":792680,"name":"Belgrade","cod":200}