{"coord":{"lon":20.4612,"lat":44.8125},"weather":[{"id":500,"main":"Rain","description":"light rain","icon":"10n"}],"base":"stations","main":{"temp":6.42,"feels_like":5.52,"temp_min":4.66,"temp_max":6.81,"pressure":1017,"humidity":72,"sea_level":1017,"grnd_level":1002},"visibility":10000,"wind":{"speed":1.54,"deg":100},"rain":{"1h":0.49},"clouds":{"all":0},"dt":1740539424,"sys":{"type":2,"id":2037836,"country":"RS","sunrise":1740547278,"sunset":1740586869},"timezone":3600,"id":792680,"name":"Belgrade","cod":200}