{"coord":{"lon":20.4612,"lat":44.8125},"weather":[{"id":800,"main":"Clear","description":"clear sky","icon":"01n"}],"base":"stations","main":{"temp":16.09,"feels_like":15.09,"temp_min":14.66,"temp_max":16.3,"pressure":1001,"humidity":51,"sea_level":1001,"grnd_level":988},"visibility":10000,"wind":{"speed":3.13,"deg":186,"gust":4.47},"clouds":{"all":0},"dt":1778789769,"sys":{"type":2,"id":2037836,"country":"RS","sunrise":1778728272,"sunset":1778781477},"timezone":7200,"id":865971,"name":"Stari Grad","cod":200}