{"coord":{"lon":20.46,"lat":44.81},"weather":[{"id":803,"main":"Clouds","description":"broken clouds","icon":"04n"}],"base":"stations","main":{"temp":3.12,"feels_like":-0.52,"temp_min":2.66,"temp_max":3.77,"pressure":1010,"humidity":80,"sea_level":1010,"grnd_level":994},"visibility":10000,"wind":{"speed":4.12,"deg":100},"clouds":{"all":75},"dt":1769917261,"sys":{"type":2,"id":2037836,"country":"RS","sunrise":1769925472,"sunset":1769960726},"timezone":3600,"id":865971,"name":"Stari Grad","cod":200}