{"coord":{"lon":20.46,"lat":44.81},"weather":[{"id":602,"main":"Snow","description":"heavy snow","icon":"13d"}],"base":"stations","main":{"temp":-2.53,"feels_like":-4.71,"temp_min":-2.96,"temp_max":-2.08,"pressure":1029,"humidity":85,"sea_level":1029,"grnd_level":1012},"visibility":6000,"wind":{"speed":1.54,"deg":360},"snow":{"1h":5.01},"clouds":{"all":100},"dt":1736934980,"sys":{"type":2,"id":2037836,"country":"RS","sunrise":1736921526,"sunset":1736954557},"timezone":3600,"id":792680,"name":"Belgrade","cod":200}