{"coord":{"lon":20.46,"lat":44.81},"weather":[{"id":501,"main":"Rain","description":"moderate rain","icon":"10d"}],"base":"stations","main":{"temp":13.73,"feels_like":12.59,"temp_min":11.92,"temp_max":14.04,"pressure":1019,"humidity":55,"sea_level":1019,"grnd_level":1003},"visibility":10000,"wind":{"speed":4.12,"deg":100},"rain":{"1h":1.64},"clouds":{"all":0},"dt":1759035373,"sys":{"type":2,"id":2037836,"country":"RS","sunrise":1759033938,"sunset":1759076714},"timezone":7200,"id":865971,"name":"Stari Grad","cod":200}