{"location":{"name":"Belgrade","region":"Central Serbia","country":"Serbia","lat":44.8,"lon":20.47,"tz_id":"Europe/Belgrade","localtime_epoch":1673034991,"localtime":"2023-01-06 20:56"},"current":{"last_updated_epoch":1673034300,"last_updated":"2023-01-06 20:45","temp_c":4.0,"temp_f":39.2,"is_day":0,"condition":{"text":"Clear","icon":"//cdn.weatherapi.com/weather/64x64/night/113.png","code":1000},"wind_mph":2.2,"wind_kph":3.6,"wind_degree":10,"wind_dir":"N","pressure_mb":1025.0,"pressure_in":30.27,"precip_mm":0.0,"precip_in":0.0,"humidity":93,"cloud":0,"feelslike_c":3.6,"feelslike_f":38.5,"vis_km":8.0,"vis_miles":4.0,"uv":1.0,"gust_mph":4.0,"gust_kph":6.5}}