{"coord":{"lon":20.46,"lat":44.81},"weather":[{"id":741,"main":"Fog","description":"fog","icon":"50d"},{"id":600,"main":"Snow","description":"light snow","icon":"13d"}],"base":"stations","main":{"temp":-0.16,"feels_like":-3.28,"temp_min":-1.96,"temp_max":0.42,"pressure":1026,"humidity":90,"sea_level":1026,"grnd_level":1009},"visibility":250,"wind":{"speed":2.57,"deg":250},"snow":{"1h":0.12},"clouds":{"all":100},"dt":1735996172,"sys":{"type":2,"id":2037836,"country":"RS","sunrise":1735971338,"sunset":1736003414},"timezone":3600,"id":792680,"name":"Belgrade","cod":200}