{"coord":{"lon":20.46,"lat":44.81},"weather":[{"id":701,"main":"Mist","description":"mist","icon":"50d"},{"id":500,"main":"Rain","description":"light rain","icon":"10d"}],"base":"stations","main":{"temp":7.47,"feels_like":5.11,"temp_min":6.58,"temp_max":7.92,"pressure":1013,"humidity":99},"visibility":2500,"wind":{"speed":3.6,"deg":20},"rain":{"1h":0.21},"clouds":{"all":100},"dt":1700654181,"sys":{"type":2,"id":2037836,"country":"RS","sunrise":1700631842,"sunset":1700665479},"timezone":3600,"id":865971,"name":"Stari Grad","cod":200}