{"coord":{"lon":20.46,"lat":44.81},"weather":[{"id":502,"main":"Rain","description":"heavy intensity rain","icon":"10n"}],"base":"stations","main":{"temp":7.07,"feels_like":7.07,"temp_min":6.92,"temp_max":7.08,"pressure":1027,"humidity":85,"sea_level":1027,"grnd_level":1011},"visibility":10000,"wind":{"speed":0.51,"deg":0},"rain":{"1h":6.48},"clouds":{"all":75},"dt":1740858982,"sys":{"type":2,"id":2037836,"country":"RS","sunrise":1740806168,"sunset":1740846313},"timezone":3600,"id":792680,"name":"Belgrade","cod":200}