{"coord":{"lon":20.4612,"lat":44.8125},"weather":[{"id":803,"main":"Clouds","description":"broken clouds","icon":"04d"}],"base":"stations","main":{"temp":12.85,"feels_like":11.84,"temp_min":11.69,"temp_max":13.54,"pressure":1025,"humidity":63,"sea_level":1025,"grnd_level":1011},"visibility":10000,"wind":{"speed":0.45,"deg":334,"gust":1.79},"clouds":{"all":53},"dt":1772705769,"sys":{"type":2,"id":2037836,"country":"RS","sunrise":1772687371,"sunset":1772728212},"timezone":3600,"id":865971,"name":"Stari Grad","cod":200}