{"coord":{"lon":20.46,"lat":44.81},"weather":[{"id":602,"main":"Snow","description":"heavy snow","icon":"13d"}],"base":"stations","main":{"temp":0.32,"feels_like":-2.16,"temp_min":-0.08,"temp_max":0.42,"pressure":1021,"humidity":63,"sea_level":1021,"grnd_level":1004},"visibility":10000,"wind":{"speed":2.06,"deg":60},"snow":{"1h":5.46},"clouds":{"all":75},"dt":1739692584,"sys":{"type":2,"id":2037836,"country":"RS","sunrise":1739684247,"sunset":1739722037},"timezone":3600,"id":792680,"name":"Belgrade","cod":200}