{"coord":{"lon":20.4631,"lat":44.8083},"weather":[{"id":802,"main":"Clouds","description":"scattered clouds","icon":"03n"}],"base":"stations","main":{"temp":9.5,"feels_like":7.11,"temp_min":8.76,"temp_max":9.69,"pressure":1010,"humidity":89,"sea_level":1010,"grnd_level":994},"visibility":10000,"wind":{"speed":4.63,"deg":280},"clouds":{"all":40},"dt":1726260703,"sys":{"type":2,"id":2037836,"country":"RS","sunrise":1726200893,"sunset":1726246402},"timezone":7200,"id":865971,"name":"Stari Grad","cod":200}