{"coord":{"lon":20.4612,"lat":44.8125},"weather":[{"id":501,"main":"Rain","description":"moderate rain","icon":"10d"}],"base":"stations","main":{"temp":17.41,"feels_like":16.8,"temp_min":16.33,"temp_max":17.41,"pressure":1007,"humidity":61,"sea_level":1007,"grnd_level":992},"visibility":10000,"wind":{"speed":1.34,"deg":0,"gust":1.34},"rain":{"1h":1.45},"clouds":{"all":100},"dt":1741949505,"sys":{"type":2,"id":2037836,"country":"RS","sunrise":1741927956,"sunset":1741970534},"timezone":3600,"id":865971,"name":"Stari Grad","cod":200}