{"coord":{"lon":20.4612,"lat":44.8125},"weather":[{"id":800,"main":"Clear","description":"clear sky","icon":"01d"}],"base":"stations","main":{"temp":28.32,"feels_like":27.95,"temp_min":27.44,"temp_max":28.69,"pressure":1014,"humidity":40,"sea_level":1014,"grnd_level":999},"visibility":10000,"wind":{"speed":4.63,"deg":290},"clouds":{"all":0},"dt":1753968369,"sys":{"type":2,"id":2037836,"country":"RS","sunrise":1753932168,"sunset":1753985167},"timezone":7200,"id":792680,"name":"Belgrade","cod":200}