{"coord":{"lon":20.46,"lat":44.81},"weather":[{"id":800,"main":"Clear","description":"clear sky","icon":"01n"}],"base":"stations","main":{"temp":18.97,"feels_like":19.01,"temp_min":16.55,"temp_max":19.3,"pressure":1016,"humidity":80,"sea_level":1016,"grnd_level":1000},"visibility":10000,"wind":{"speed":1.54,"deg":179,"gust":1.54},"clouds":{"all":8},"dt":1722038178,"sys":{"type":2,"id":2037836,"country":"RS","sunrise":1722050318,"sunset":1722103827},"timezone":7200,"id":792680,"name":"Belgrade","cod":200}