{"coord":{"lon":20.46,"lat":44.81},"weather":[{"id":300,"main":"Drizzle","description":"light intensity drizzle","icon":"09n"}],"base":"stations","main":{"temp":6.34,"feels_like":4.05,"temp_min":5.92,"temp_max":6.53,"pressure":1020,"humidity":94,"sea_level":1020,"grnd_level":1004},"visibility":6000,"wind":{"speed":3.09,"deg":270},"clouds":{"all":75},"dt":1765151779,"sys":{"type":2,"id":2037836,"country":"RS","sunrise":1765173781,"sunset":1765205845},"timezone":3600,"id":792680,"name":"Belgrade","cod":200}