{"coord":{"lon":20.46,"lat":44.81},"weather":[{"id":800,"main":"Clear","description":"clear sky","icon":"01n"}],"base":"stations","main":{"temp":21.52,"feels_like":21.58,"temp_min":19.32,"temp_max":22.11,"pressure":1021,"humidity":71,"sea_level":1021,"grnd_level":1005},"visibility":10000,"wind":{"speed":3.13,"deg":182,"gust":3.58},"clouds":{"all":7},"dt":1781908762,"sys":{"type":2,"id":2037836,"country":"RS","sunrise":1781923917,"sunset":1781980042},"timezone":7200,"id":792680,"name":"Belgrade","cod":200}