{"coord":{"lon":20.46,"lat":44.81},"weather":[{"id":500,"main":"Rain","description":"light rain","icon":"10d"}],"base":"stations","main":{"temp":6.04,"feels_like":3.69,"temp_min":5.97,"temp_max":6.92,"pressure":1016,"humidity":87,"sea_level":1016,"grnd_level":1001},"visibility":6000,"wind":{"speed":3.09,"deg":30},"rain":{"1h":0.5},"clouds":{"all":75},"dt":1771915278,"sys":{"type":2,"id":2037836,"country":"RS","sunrise":1771910706,"sunset":1771949885},"timezone":3600,"id":792680,"name":"Belgrade","cod":200}