{"coord":{"lon":20.4612,"lat":44.8125},"weather":[{"id":800,"main":"Clear","description":"clear sky","icon":"01d"}],"base":"stations","main":{"temp":19.69,"feels_like":18.45,"temp_min":19.63,"temp_max":19.81,"pressure":1020,"humidity":28,"sea_level":1020,"grnd_level":1005},"visibility":10000,"wind":{"speed":7.2,"deg":350},"clouds":{"all":0},"dt":1777220173,"sys":{"type":2,"id":2037836,"country":"RS","sunrise":1777174547,"sunset":1777224953},"timezone":7200,"id":865971,"name":"Stari Grad","cod":200}