{"coord":{"lon":20.46,"lat":44.81},"weather":[{"id":800,"main":"Clear","description":"clear sky","icon":"01n"}],"base":"stations","main":{"temp":14.21,"feels_like":13.28,"temp_min":14.04,"temp_max":15.44,"pressure":1017,"humidity":61,"sea_level":1017,"grnd_level":1002},"visibility":10000,"wind":{"speed":3.09,"deg":120},"clouds":{"all":0},"dt":1761760580,"sys":{"type":2,"id":2037836,"country":"RS","sunrise":1761714718,"sunset":1761751895},"timezone":3600,"id":865971,"name":"Stari Grad","cod":200}