{"coord":{"lon":20.46,"lat":44.81},"weather":[{"id":802,"main":"Clouds","description":"scattered clouds","icon":"03n"}],"base":"stations","main":{"temp":22.4,"feels_like":22.94,"temp_min":20.44,"temp_max":22.64,"pressure":1016,"humidity":86,"sea_level":1016,"grnd_level":1000},"visibility":10000,"wind":{"speed":1.69,"deg":113,"gust":1.79},"clouds":{"all":35},"dt":1720580185,"sys":{"type":2,"id":2037836,"country":"RS","sunrise":1720580532,"sunset":1720635870},"timezone":7200,"id":865971,"name":"Stari Grad","cod":200}