{"coord":{"lon":20.46,"lat":44.81},"weather":[{"id":802,"main":"Clouds","description":"scattered clouds","icon":"03d"}],"base":"stations","main":{"temp":19.74,"feels_like":19.75,"temp_min":18.92,"temp_max":21.02,"pressure":1008,"humidity":76,"sea_level":1008,"grnd_level":993},"visibility":10000,"wind":{"speed":1.48,"deg":267,"gust":1.31},"clouds":{"all":40},"dt":1722570976,"sys":{"type":2,"id":2037836,"country":"RS","sunrise":1722569123,"sunset":1722621799},"timezone":7200,"id":792680,"name":"Belgrade","cod":200}