{"coord":{"lon":20.46,"lat":44.81},"weather":[{"id":803,"main":"Clouds","description":"broken clouds","icon":"04n"}],"base":"stations","main":{"temp":28.17,"feels_like":29.36,"temp_min":24.32,"temp_max":28.19,"pressure":1018,"humidity":57,"sea_level":1018,"grnd_level":1003},"visibility":10000,"wind":{"speed":3.13,"deg":180,"gust":3.58},"clouds":{"all":56},"dt":1782683201,"sys":{"type":2,"id":2037836,"country":"RS","sunrise":1782615261,"sunset":1782671290},"timezone":7200,"id":792680,"name":"Belgrade","cod":200}