{"coord":{"lon":20.46,"lat":44.81},"weather":[{"id":501,"main":"Rain","description":"moderate rain","icon":"10d"}],"base":"stations","main":{"temp":17.69,"feels_like":17.34,"temp_min":15.92,"temp_max":18.04,"pressure":1016,"humidity":70,"sea_level":1016,"grnd_level":1000},"visibility":10000,"wind":{"speed":7.2,"deg":140},"rain":{"1h":3.87},"clouds":{"all":0},"dt":1744862230,"sys":{"type":2,"id":2037836,"country":"RS","sunrise":1744861808,"sunset":1744910692},"timezone":7200,"id":792680,"name":"Belgrade","cod":200}