{"coord":{"lon":20.46,"lat":44.81},"weather":[{"id":804,"main":"Clouds","description":"overcast clouds","icon":"04n"}],"base":"stations","main":{"temp":2.54,"feels_like":0.44,"temp_min":0.92,"temp_max":3.21,"pressure":1023,"humidity":83,"sea_level":1023,"grnd_level":1006},"visibility":266,"wind":{"speed":2.06,"deg":204,"gust":2.76},"clouds":{"all":100},"dt":1768413509,"sys":{"type":2,"id":2037836,"country":"RS","sunrise":1768371166,"sunset":1768404063},"timezone":3600,"id":792680,"name":"Belgrade","cod":200}